spy/__init__.py
spy/page.py
spy/page_set.py
spy/spy.py
spy/web_crawler.py
spy/web_parser.py
spy_crawler-0.1.2.dist-info/METADATA
spy_crawler-0.1.2.dist-info/WHEEL
spy_crawler-0.1.2.dist-info/RECORD
