Metadata-Version: 2.1
Name: spy_crawler
Version: 0.1.2
Summary: 
Author: Rafael Fonseca
Author-email: justonedev42@gmail.com
Requires-Python: >=3.11,<4.0
Classifier: Programming Language :: Python :: 3
Classifier: Programming Language :: Python :: 3.11
Classifier: Programming Language :: Python :: 3.12
Requires-Dist: httpx[http2] (>=0.26.0,<0.27.0)
Requires-Dist: pandas (>=2.2.0,<3.0.0)
Requires-Dist: parsel (>=1.8.1,<2.0.0)
Requires-Dist: tabulate (>=0.9.0,<0.10.0)
